reviewmywork/__init__.py
reviewmywork/main.py
reviewmywork/reviewer.py
reviewmywork/schemas.py
reviewmywork/tools.py
reviewmywork-0.1.1.dist-info/WHEEL
reviewmywork-0.1.1.dist-info/entry_points.txt
reviewmywork-0.1.1.dist-info/METADATA
reviewmywork-0.1.1.dist-info/RECORD
