Metadata-Version: 2.4
Name: reviewmywork
Version: 0.1.1
Summary: AI Code Review Agent
Author: Adrian Quiroga
Author-email: Adrian Quiroga <git@adrq.net>
License-Expression: MIT
Requires-Dist: aisuite[all]>=0.1.11
Requires-Dist: docstring-parser>=0.17.0
Requires-Dist: gitpython>=3.1.45
Requires-Dist: pre-commit>=4.2.0
Requires-Dist: pydantic>=2.11.7
Requires-Dist: python-dotenv>=1.1.1
Requires-Dist: rich>=14.1.0
Requires-Dist: typer>=0.16.0
Requires-Dist: unidiff>=0.7.5
Requires-Python: >=3.10
